gpr1dfusion.py
gpr1dfusion-1.1.0.data/scripts/GIG_test.py
gpr1dfusion-1.1.0.data/scripts/M52_test.py
gpr1dfusion-1.1.0.data/scripts/RQ_test.py
gpr1dfusion-1.1.0.dist-info/LICENSE
gpr1dfusion-1.1.0.dist-info/METADATA
gpr1dfusion-1.1.0.dist-info/WHEEL
gpr1dfusion-1.1.0.dist-info/top_level.txt
gpr1dfusion-1.1.0.dist-info/RECORD
