Metadata-Version: 2.1
Name: gpr1dfusion
Version: 1.1.0
Summary: Classes for Gaussian Process Regression fitting of 1D fusion data with errorbars, built on GPR1D package.
Home-page: https://gitlab.com/aaronkho/gpr1dfusion.git
Author: Aaron Ho
Author-email: a.ho@differ.nl
License: MIT
Keywords: gaussian process regression,1D data fitting,kriging,OMFIT,fusion data
Platform: UNKNOWN
Classifier: Development Status :: 4 - Beta
Classifier: Intended Audience :: Science/Research
Classifier: Topic :: Utilities
Classifier: License :: OSI Approved :: MIT License
Classifier: Natural Language :: English
Classifier: Programming Language :: Python :: 2.7
Classifier: Programming Language :: Python :: 3.5
Requires-Dist: GPR1D (>=1.2.0)
Requires-Dist: numpy
Provides-Extra: test
Requires-Dist: coverage ; extra == 'test'
Requires-Dist: pytest ; extra == 'test'
Requires-Dist: pytest-cov ; extra == 'test'
